<?xml version="1.0" encoding="UTF-8"?>
<bundle>
  <webconferencing>
    <admin>
      <page>Elektronisch vergaderen</page>
      <title>Administratie van elektronisch vergaderen</title>
      <info>'Elektonisch vergaderen' kan door verschillende providers worden afgehandeld. U kunt de provider die u nodig hebt inschakelen en de instellingen configureren.</info>
      <provider>Provider</provider>
      <description>Beschrijving</description>
      <active>Actieve</active>
      <actions>Acties</actions>
    </admin>
  </webconferencing>
</bundle>
