<?xml version="1.0" encoding="UTF-8"?>
<bundle>
  <webconferencing>
    <admin>
      <page>Web conferencing</page>
      <title>Amministrazione di web conferencing</title>
      <info>Web Conferencing possono essere gestite da diversi fornitori. È possibile abilitare il provider necessario e configurare le configurazioni.</info>
      <provider>Fornitore</provider>
      <description>Descrizione</description>
      <active>Attiva</active>
      <actions>Azioni</actions>
    </admin>
  </webconferencing>
</bundle>
